kalcal/__init__.py
kalcal/datasets/__init__.py
kalcal/datasets/antenna_tables/__init__.py
kalcal/datasets/antenna_tables/kat-7.itrf.txt
kalcal/datasets/gains/__init__.py
kalcal/datasets/gains/normal.npy
kalcal/datasets/sky_models/MODEL-1.txt
kalcal/datasets/sky_models/MODEL-4.txt
kalcal/datasets/sky_models/MODEL-50.txt
kalcal/datasets/sky_models/__init__.py
kalcal/filters/__init__.py
kalcal/filters/ekf.py
kalcal/filters/enkf.py
kalcal/filters/iekf.py
kalcal/generation/__init__.py
kalcal/generation/create_ms.py
kalcal/generation/from_ms.py
kalcal/generation/loader.py
kalcal/generation/normal_gains.py
kalcal/generation/parser.py
kalcal/generation/phase_gains.py
kalcal/plotting/__init__.py
kalcal/plotting/multiplot.py
kalcal/plotting/plotops.py
kalcal/plotting/singleplot.py
kalcal/smoothers/__init__.py
kalcal/smoothers/eks.py
kalcal/tools/__init__.py
kalcal/tools/jacobian.py
kalcal/tools/sparseops.py
kalcal/tools/statistics.py
kalcal/tools/utils.py
kalcal/tuners/__init__.py
kalcal/tuners/equations.py
tests/__init__.py
tests/conftest.py
tests/test_imports.py
tests/test_jacobian.py
tests/test_measure.py
tests/test_rime.py
tests/fixtures/__init__.py
tests/fixtures/data.py
tests/fixtures/generate.py
tests/fixtures/lsm.py
tests/fixtures/matrix.py
tests/fixtures/ms.py
tests/fixtures/tools.py
kal_cal-0.0.1.dist-info/AUTHORS.rst
kal_cal-0.0.1.dist-info/LICENSE
kal_cal-0.0.1.dist-info/METADATA
kal_cal-0.0.1.dist-info/WHEEL
kal_cal-0.0.1.dist-info/top_level.txt
kal_cal-0.0.1.dist-info/RECORD
