Metadata-Version: 2.1
Name: kal-cal
Version: 0.0.1
Summary: kalman Filter and SmootherRadio Interoferometric Calibration
Home-page: https://github.com/brianwelman2/kal-cal.git
Author: Brian Welman
Author-email: brianallisterwelman@gmail.com
License: UNKNOWN
Platform: UNKNOWN
Classifier: Natural Language :: English
Classifier: Programming Language :: Python :: 3
Classifier: Programming Language :: Python :: 3.6
Classifier: License :: OSI Approved :: MIT License
Classifier: Operating System :: Unix
Requires-Python: >=3.6
Requires-Dist: PyYAML
Requires-Dist: astro-tigger-lsm
Requires-Dist: codex-africanus
Requires-Dist: dask
Requires-Dist: dask-ms
Requires-Dist: matplotlib
Requires-Dist: numba
Requires-Dist: numpy
Requires-Dist: packratt
Requires-Dist: pytest
Requires-Dist: scipy
Requires-Dist: simms
Requires-Dist: tabulate
Requires-Dist: toolz
Requires-Dist: tqdm
Requires-Dist: xarray
